README.md
setup.py
pyRepRapComm/__init__.py
pyRepRapComm.egg-info/PKG-INFO
pyRepRapComm.egg-info/SOURCES.txt
pyRepRapComm.egg-info/dependency_links.txt
pyRepRapComm.egg-info/not-zip-safe
pyRepRapComm.egg-info/top_level.txt