Metadata-Version: 1.0
Name: pyRepRapComm
Version: 0.1
Summary: Simple Module to Support Communications with Printers running RepRapFirmware
Home-page: http://github.com/ktelep/pyRepRapComm
Author: Kurt Telep
Author-email: ktelep@gmail.com
License: MIT
Platform: UNKNOWN
